llm_xray/__init__.py
llm_xray/core.py
llm_xray-0.1.0.dist-info/METADATA
llm_xray-0.1.0.dist-info/WHEEL
llm_xray-0.1.0.dist-info/top_level.txt
llm_xray-0.1.0.dist-info/RECORD
