Metadata-Version: 2.4
Name: llm_xray
Version: 0.1.0
Summary: A real-time visualization and training tool for GPT-2
Project-URL: Homepage, https://github.com/vedant/llm_xray
Requires-Dist: torch
Requires-Dist: transformers
Requires-Dist: rich
Requires-Dist: fastapi
Requires-Dist: uvicorn
Requires-Dist: requests
